<?xml version="1.0" encoding="UTF-8"?>
<config>
		<lang_name>Қазақ(kz)</lang_name>
		<lang>kz</lang>
		<str id="NULL">*empty*</str>
		<str id="BUTTON_OK">Ok</str>
		<str id="BUTTON_CANCEL">Бас тарту</str>
		<str id="BUTTON_APPLY">Қолдану</str>
		<str id="BUTTON_SAVE">Сақтау</str>
		<str id="BUTTON_SAVE_AS">Басқаша сақтау...</str>
		<str id="BUTTON_DELETE">Жою</str>
		<str id="BUTTON_BROWSE">Шолу...</str>
		<str id="BUTTON_CREATE">Құру</str>
		<str id="BUTTON_CAPTURE">Жазу</str>
		<str id="BUTTON_START_READY">Бастау</str>
		<str id="BUTTON_START_LIVE">Бастау</str>
		<str id="BUTTON_STOP_MEASUREMENT">Өлшеу...</str>
		<str id="BUTTON_YES">Ия</str>
		<str id="BUTTON_NO">Жоқ</str>
		<str id="BUTTON_ALL">Барлығы</str>
		<str id="BUTTON_ON">Қос.</str>
		<str id="BUTTON_OFF">Өшір.</str>
		<str id="BUTTON_HIDE">Жасыру</str>
		<str id="BUTTON_OPEN">Ашу...</str>
		<str id="BUTTON_SET">Орнату</str>
		<str id="BUTTON_RESET">Қалпына келтіру</str>
		<str id="BUTTON_UNREGISTER">Тіркеуден бас тарту</str>
		<str id="BUTTON_SETTINGS">Баптаулар...</str>
		<str id="BUTTON_DEFAULTS">Алдын ала орнатулар</str>
		<str id="BUTTON_QUALITY">Сапасы</str>
		<str id="BUTTON_0">0</str>
		<str id="BUTTON_1">1</str>
		<str id="BUTTON_2">2</str>
		<str id="BUTTON_3">3</str>
		<str id="BUTTON_4">4</str>
		<str id="BUTTON_5">5</str>
		<str id="BUTTON_6">6</str>
		<str id="BUTTON_7">7</str>
		<str id="BUTTON_8">8</str>
		<str id="BUTTON_9">9</str>
		<str id="MENU_FILE">Файл</str>
		<str id="MENU_FILE_AVI_SETTINGS">AVI: Баптаулар</str>
		<str id="MENU_FILE_AVI_CAPTURE1">AVI: Жазуды бастау</str>
		<str id="MENU_FILE_AVI_CAPTURE2">AVI: Жазуды тоқтату</str>
		<str id="MENU_FILE_AVI_TMP_CAPTURE1">AVI: Жазуды бастау (экраннан)</str>
		<str id="MENU_FILE_AVI_TMP_CAPTURE2">AVI: Жазуды тоқтату (экраннан)</str>
		<str id="MENU_FILE_IMAGE_CAPTURE">Кескінді қармап алу</str>
		<str id="MENU_FILE_SAVE_IMAGE">Кескінді сақтау</str>
		<str id="MENU_FILE_DBFOLDER">Дерекқор каталогы...</str>
		<str id="MENU_FILE_EXIT">Шығу</str>
		<str id="MENU_FILE_PRINT">Басып шығару</str>
		<str id="MENU_FILE_PRINT_PREVIEW">Алдын ала қарау</str>
		<str id="MENU_FILE_PRINT_SETUP">Басып шығаруды баптау...</str>
		<str id="MENU_FILE_PAGE_SETUP">Бет параметрлері...</str>
		<str id="MENU_FILE_OPEN_LOG">Ашу VI...</str>
		<str id="MENU_FILE_OPEN">Ашу</str>
		<str id="MENU_FILE_SET_ARCHIVE_FOLDER">Мұрағат папкасын орнату...</str>
		<str id="MENU_FILE_DELETE">Жою…</str>
		<str id="MENU_FILE_NEW_RECORD">Жазуды құру...</str>
		<str id="MENU_FILE_SAVE_AS_TABLE">Кесте ретінде сақтау...</str>
		<str id="MENU_FILE_SAVE_SETTINGS">Баптауларды сақтау...</str>
		<str id="MENU_FILE_LOAD_SETTINGS">Баптауларды жүктеу...</str>
		<str id="MENU_VIEW">Түрі</str>
		<str id="MENU_VIEW_SIMPLE">Қарапайым көрініс</str>
		<str id="MENU_VIEW_TOOLBARS">Құралдар панелдер</str>
		<str id="MENU_VIEW_TOOLBAR">Құралдар панелі</str>
		<str id="MENU_VIEW_APPLOOK">Безендіру стильдері</str>
		<str id="MENU_VIEW_STATUSBAR">Күй жолағы</str>
		<str id="MENU_VIEW_INFOBAR">Ақпараттық панель</str>
		<str id="MENU_VIEW_LDBAR">LD панель</str>
		<str id="MENU_VIEW_BUTTONS">Батырмалар</str>
		<str id="MENU_VIEW_GRAPHS">Графиктер</str>
		<str id="MENU_VIEW_HISTS">Жиілікті талдау нәтижелері</str>
		<str id="MENU_VIEW_HISTS_BT">Тестілеу нәтижелері</str>
		<str id="MENU_VIEW_VIDEOWINDOW">Бейне терезесі</str>
		<str id="MENU_VIEW_STATUSWINDOW">Мәртебе терезесі</str>
		<str id="MENU_VIEW_LDWINDOW">Жалғандық индикаторы</str>
		<str id="MENU_VIEW_OVERVIEW">Қарау</str>
		<str id="MENU_VIEW_MODE">Режим</str>
		<str id="MENU_VIEW_MODE_TOOLBAR">Құралдар панелі</str>
		<str id="MENU_VIEW_MODE_VI0A">VI (N Am)</str>
		<str id="MENU_VIEW_MODE_VI1A">VI (10 Am)</str>
		<str id="MENU_VIEW_MODE_VI2A">VI (2 Am)</str>
		<str id="MENU_VIEW_MODE_VI0B">VI (N F)</str>
		<str id="MENU_VIEW_MODE_VI1B">VI (10 F)</str>
		<str id="MENU_VIEW_MODE_VI2B">VI (2 F)</str>
		<str id="MENU_VIEW_MODE_SRC">SRC</str>
		<str id="MENU_VIEW_MODE_SRC_A">SRC Am</str>
		<str id="MENU_VIEW_MODE_SRC_B">SRC F</str>
		<str id="MENU_VIEW_MODE_DELTA_A">DELTA Am</str>
		<str id="MENU_VIEW_MODE_DELTA_B">DELTA F</str>
		<str id="MENU_VIEW_MODE_DELTA_FA">DELTA FAm</str>
		<str id="MENU_VIEW_MODE_DELTA_FB">DELTA FF</str>
		<str id="MENU_VIEW_MODE_A">режим Am</str>
		<str id="MENU_VIEW_MODE_B">режим F</str>
		<str id="MENU_VIEW_MODE_MFN">Меңзермен басқару</str>
		<str id="MENU_VIEW_MODE_MHIST">Сызықтар</str>
		<str id="MENU_VIEW_MODE_SHIST">Сомалар</str>
		<str id="MENU_VIEW_MODE_SHOW">Көрсету</str>
		<str id="MENU_VIEW_MODE_AURA">Аура</str>
		<str id="MENU_VIEW_MODE_AURA_A">Аура A</str>
		<str id="MENU_VIEW_MODE_AURA_B">Аура F</str>
		<str id="MENU_VIEW_MODE_AURA_0">Аурасыз</str>
		<str id="MENU_VIEW_MODE_WHITEBG">Ақ фон</str>
		<str id="MENU_VIEW_MODE_AVITIMER">AVI уақыты</str>
		<str id="MENU_VIEW_MODE_CENTER">Орталық</str>
		<str id="MENU_VIEW_MODE_TITLE">Тақырып</str>
		<str id="MENU_VIEW_MODE_TOOLTIPS">Қалқыма терезе</str>
		<str id="MENU_VIEW_PRESET">Алдын ала орнатулар</str>
		<str id="MENU_VIEW_PRESET_VI">VI</str>
		<str id="MENU_VIEW_PRESET_AV">AV</str>
		<str id="MENU_VIEW_PRESET_R">R</str>
		<str id="MENU_VIEW_PRESET_AR">AR</str>
		<str id="MENU_VIEW_PRESET_LD">LD</str>
		<str id="MENU_VIEW_PRESET_RELAX">Relax</str>
		<str id="MENU_VIEW_LOCK_POS">Позицияны бекіту</str>
		<str id="MENU_VIEW_ZOOM_IN">Үлкейту</str>
		<str id="MENU_VIEW_ZOOM_OUT">Азайту</str>
		<str id="MENU_VIEW_ZOOM_NX_IN">X [1:%i] Үлкейту</str>
		<str id="MENU_VIEW_ZOOM_NX_OUT">X [1:%i] Азайту</str>
		<str id="MENU_VIEW_ZOOM_Y_IN">Y Үлкейту</str>
		<str id="MENU_VIEW_ZOOM_Y_OUT">Y Азайту</str>
		<str id="MENU_VIEW_ZOOM_X_IN">X Үлкейту</str>
		<str id="MENU_VIEW_ZOOM_X_OUT">X Азайту</str>
		<str id="MENU_EDIT">Өңдеу</str>
		<str id="MENU_SETTINGS">Баптаулар</str>
		<str id="MENU_SETTINGS_LDQ_MIX">LD сұрақтарды араластыру</str>
		<str id="MENU_SETTINGS_DEFAULTS">Алдын ала орнатулар</str>
		<str id="MENU_SETTINGS_VIDEO0">Бейне</str>
		<str id="MENU_SETTINGS_VIDEO0_AVI">AVI Файл...</str>
		<str id="MENU_SETTINGS_VIDEO0_AVI_NOSOUND">AVI файлы (дыбыссыз)...</str>
		<str id="MENU_SETTINGS_VIDEO0_AVI_RECOMPRESS">AVI файлы (+ашу)...</str>
		<str id="MENU_SETTINGS_VIDEO0_RGB8FLT">RGB8 қысу</str>
		<str id="MENU_SETTINGS_VIDEO0_STOP">Өшіру</str>
		<str id="MENU_SETTINGS_VIDEO0_CAPTUREMODE">Жазу режимі</str>
		<str id="MENU_SETTINGS_VIDEO0_ROTATE_CW">CW бұрылысы</str>
		<str id="MENU_SETTINGS_VIDEO0_ROTATE_CCW">CCW бұрылысы</str>
		<str id="MENU_SETTINGS_VIDEO0_MIRROR_X">Х көрсету</str>
		<str id="MENU_SETTINGS_VIDEO0_MIRROR_Y">Y көрсету</str>
		<str id="MENU_SETTINGS_VIDEO0_SAVE">Баптауларды сақтау</str>
		<str id="MENU_SETTINGS_AUDIO0">Дыбыс</str>
		<str id="MENU_SETTINGS_AUDIO0_CONFIG">Параметрлер...</str>
		<str id="MENU_SETTINGS_AUDIO0_LEVEL">Шегі</str>
		<str id="MENU_SETTINGS_AUDIO0_DISABLE">Дыбысты өшіру</str>
		<str id="MENU_SETTINGS_LANG">Тіл</str>
		<str id="MENU_SETTINGS_AI">AI</str>
		<str id="MENU_SETTINGS_RECORD_GROUP">Жазулар тобы</str>
		<str id="MENU_SETTINGS_RECORD_GROUP_DEFAULT">Жалпы</str>
		<str id="MENU_SETTINGS_SKYPESTATUS">Skype мәртебесі</str>
		<str id="MENU_SETTINGS_VIDEVICE">VIDevice</str>
		<str id="MENU_SETTINGS_LOCK">Бұғаттау</str>
		<str id="MENU_SETTINGS_UNLOCK">Бұғаттауды ашу</str>
		<str id="MENU_SETTINGS_MITSAREEG">МИЦАР ЭЭГ (бұл Мitsar фирмасының электроэнцефалографы)</str>
		<str id="MENU_SETTINGS_AI20">AI 20s/5s</str>
		<str id="MENU_SETTINGS_SAVE_PHOTO">Фотосуретті сақтау</str>
		
		<str id="MENU_SETTINGS_MASK">Маска бейнесі</str>
		<str id="MENU_SETTINGS_MASK_LOAD">Жүктеу...</str>
		<str id="MENU_SETTINGS_MASK_EXPORT">Сақтау…</str>
		<str id="MENU_SETTINGS_MASK_RESET">Қалпына келтіру</str>
		<str id="MENU_SETTINGS_MASK_EDIT">Түзету режимі</str>
		<str id="MENU_SETTINGS_CAPTURE">Жазу арнасы</str>
		<str id="MENU_SETTINGS_SKIN">Безендіру</str>
		<str id="MENU_SETTINGS_SKIN_DEFAULT">Классикалық түр</str>
		<str id="MENU_SETTINGS_AUTOSTART">Авто старт</str>
		<str id="MENU_SETTINGS_SETPASSWORD">Құпия сөзді орнату</str>
		<str id="MENU_SETTINGS_ENABLE_QT">Сапа сынағы</str>
		<str id="MENU_SETTINGS_MEASURE_FAST">Жылдам тест</str>
		<str id="MENU_SETTINGS_SMART_MEASURE">Ақылды өлшем</str>
		<str id="MENU_ACTION">Әрекеттер</str>
		<str id="MENU_ACTION_PAUSE">Кідірту</str>
		<str id="MENU_ACTION_RESET">Қалпына келтіру</str>
		<str id="MENU_ACTION_PLAY">Бастау</str>
		<str id="MENU_ACTION_RESETTIMER">Есептегіштерді қалпына келтіру</str>
		<str id="MENU_ACTION_MEASUREMENT">Өлшеу</str>
		<str id="MENU_ACTION_HIST">Жиілікті талдау</str>
		<str id="MENU_ACTION_HIST_STARTA">Бастау H</str>
		<str id="MENU_ACTION_HIST_STARTA10">Бастау H 10с</str>
		<str id="MENU_ACTION_HIST_STARTF">Бастау S</str>
		<str id="MENU_ACTION_HIST_STARTF10">Бастау S 10с</str>
		<str id="MENU_ACTION_HIST_STARTT">Бастау T</str>
		<str id="MENU_ACTION_HIST_STARTT10">Бастау T 10с</str>
		<str id="MENU_ACTION_HIST_STOP">Тоқта</str>
		<str id="MENU_ACTION_MARKERS">Маркерлер</str>
		<str id="MENU_ACTION_MARKERS_Q0">R сұрағы</str>
		<str id="MENU_ACTION_MARKERS_Q1">C сұрағы</str>
		<str id="MENU_ACTION_MARKERS_Q2">G сұрағы</str>
		<str id="MENU_ACTION_LD_START">LD өңдеуді бастау</str>
		<str id="MENU_ACTION_LD_STOP">LD өңдеуді аяқтау</str>
		<str id="MENU_ACTION_LD_CMP_START">LD салыстыру блогын бастау</str>
		<str id="MENU_ACTION_LD_CMP_STOP">LD салыстыру блогын аяқтау</str>
		<str id="MENU_ACTION_LITELOG">Хаттаманы жазу</str>
		<str id="MENU_LD_AUTO">LD авто</str>
		<str id="MENU_LD_AUDIO">LD дыбыс</str>
		<str id="MENU_LD_MANUAL">LD қолмен</str>
		<str id="MENU_LD_TEXT">LD мәтіні</str>
		<str id="MENU_LD_LOAD">LD сауалнаманы жүктеу...</str>
		<str id="MENU_LD_EDIT">LD сауалнаманы өзгерту...</str>
		<str id="MENU_HELP">Анықтама</str>
		<str id="MENU_HELP_ABOUT">Бағдарлама туралы...</str>
		<str id="MENU_HELP_HELP">Анықтаманы шақыру...</str>
		<str id="MENU_HELP_HELP_FILE">VibraImageHelp8ru.chm</str>
		<str id="MENU_LD_CAPTURE_LDQ"> LDQ бейне жазу</str>
		<str id="MENU_LD_SHOW_ANSWER">Жауаптарды таңдау</str>
		<str id="VIDEO_FRAME_TITLE">Бейне</str>
		<str id="STATUS_FRAME_TITLE">Мәртебе</str>
		<str id="LD_FRAME_TITLE">Өтірік көрсеткіші</str>
		<str id="INFO_DEFAULTS">Алдын ала орнатулар</str>
		<str id="INFO_DEFAULT_MICRO">Алдын ала орнатулар Micro</str>
		<str id="INFO_DEFAULT_MACRO">Алдын ала орнатулар Macro</str>
		<str id="INFO_DEFAULT_LD">Алдын ала орнатулар LD</str>
		<str id="INFO_V4_FRAME_RATE">Кадр жиілігі</str>
		<str id="INFO_V4_FRAME_RATE_IN">Кіру</str>
		<str id="INFO_V4_FRAME_RATE_IN_FPS">К/ж Кіру (кадр жиілігі)</str>
		<str id="INFO_V4_FRAME_RATE_OUTF">Жылдам өңдеу</str>
		<str id="INFO_V4_FRAME_RATE_OUTF_FPS">ЖӨ к/ж (жылдам өңдеу кадрлар жиілігі)</str>
		<str id="INFO_V4_FRAME_RATE_DROPF">ЖӨ жоғалды (жылдам өңдеу кадрлары жоғалды)</str>
		<str id="INFO_V4_FRAME_RATE_MAXF">Жылдам өңдеу</str>
		<str id="INFO_V4_FRAME_RATE_OUTR">Негізгі өңдеу</str>
		<str id="INFO_V4_FRAME_RATE_OUTR_FPS">НӨ к/ж (негізгі өңдеудің кадрлар жиілігі)</str>
		<str id="INFO_V4_FRAME_RATE_DROPR">НӨ жоғалды (негізгі өңдеу кадрлары жоғалды)</str>
		<str id="INFO_V4_FRAME_RATE_MAXR">Негізгі өңдеу</str>
		<str id="INFO_V4_FRAME_RATE_PERIOD">FPS есептеу кезеңі</str>
		<str id="INFO_V4_FRAME_TIME_VIDEO">Бейне уақыты</str>
		<str id="INFO_V4_FRAME_TIME_AUDIO">Аудио уақыты</str>
		<str id="INFO_V4_MAIN">Параметрлер </str>
		<str id="INFO_V4_N">N</str>
		<str id="INFO_V4_K">K</str>
		<str id="INFO_V4_TH">L</str>
		<str id="INFO_V4_NDROP">Ағын қателері</str>
		<str id="INFO_V4_MEMORY_USAGE">RAM</str>
		<str id="INFO_V4_STAT">Статистика</str>
		<str id="INFO_V4_INTEGR0A">IntegratedN(Am)</str>
		<str id="INFO_V4_INTEGR1A">Integrated10(Am)</str>
		<str id="INFO_V4_INTEGR2A">Integrated2(Am)</str>
		<str id="INFO_V4_INTEGR0B">IntegratedN(F)</str>
		<str id="INFO_V4_INTEGR1B">Integrated10(F)</str>
		<str id="INFO_V4_INTEGR2B">Integrated2(F)</str>
		<str id="INFO_V4_ANGER">Агрессия</str>
		<str id="INFO_V4_STRESS">Стресс</str>
		<str id="INFO_V4_TENSION">Мазасыздық</str>
		<str id="INFO_V4_SUSPICIOUS">Қауіп</str>
		<str id="INFO_V4_STATUS">Күй</str>
		<str id="INFO_V4_AUDIO">Дыбыс </str>
		<str id="INFO_V4_AUDIO_LEVEL">Деңгей</str>
		<str id="INFO_V4_AUDIO_TH">Шегі</str>
		<str id="INFO_V4_AUDIO_DELAY">Кідіріс (с)</str>
		<str id="INFO_V4_AUDIO_PERIOD">Кезең (мс)</str>
		<str id="INFO_V4_AVI_OVERLOAD">AVI қайта жүктеу</str>
		<str id="INFO_V4_SIZE_W">Ені</str>
		<str id="INFO_V4_SIZE_H">Биіктігі</str>
		<str id="INFO_AUDIO_LEVEL">Дыбыс деңгейі</str>
		<str id="INFO_AUDIO_LEVEL25">Дыбыс деңгейі 25 к/с</str>
		<str id="INFO_CFG_MAIN">Негізгі</str>
		<str id="INFO_CFG_N">N</str>
		<str id="INFO_CFG_N1">N(10)</str>
		<str id="INFO_CFG_N2">N(2)</str>
		<str id="INFO_CFG_K">K</str>
		<str id="INFO_CFG_TH">L</str>
		<str id="INFO_CFG_ENGINE_THREAD_RQST">Параллельдеу</str>
		<str id="INFO_CFG_ENGINE_GPU">GPU өңдеу</str>
		<str id="INFO_CFG_CORES">Cores</str>
		<str id="INFO_AI_LIVE">AI Corona</str>
		<str id="INFO_CFG_FLT">Сүзгілер</str>
		<str id="INFO_CFG_FLT_SP">Нүкте сүзгісі</str>
		<str id="INFO_CFG_FLT_DL">Кеңейтілген</str>
		<str id="INFO_CFG_FLT_DLF">Кеңейтілген (fast)</str>
		<str id="INFO_CFG_FLT_STR">Нормаланған дельталар</str>
		<str id="INFO_CFG_FLT_MSCONT">2 контур</str>
		<str id="INFO_CFG_FLT_FPS2IN">К/ж бөлгіш</str>
		<str id="INFO_CFG_FLT_AM">Am көбейткіші</str>
		<str id="INFO_CFG_FLT_CT">Кеңістіктік сүзгі</str>
		<str id="INFO_CFG_FLT_BTFAST">BT кжб (Бұл кадр жиілігін бөлгіш. Кіріс кадр жиілігін азайту)</str>
		<str id="INFO_CFG_FLT_DIS">Өшіру *</str>
		<str id="INFO_CFG_FLT_DIS_A">Өшіру Am</str>
		<str id="INFO_CFG_FLT_DIS_B">Өшіру F</str>
		<str id="INFO_CFG_FLT_DIS_2X">Өшіру 2x(fast)</str>
		<str id="INFO_CFG_FLT_DIS_VI0">Өшіру VI(N)</str>
		<str id="INFO_CFG_FLT_DIS_VI1">Өшіру VI(10)</str>
		<str id="INFO_CFG_FLT_DIS_VI2">Өшіру VI(2)</str>
		<str id="INFO_CFG_FLT_DIS_FFTU">Өшіру FFT</str>
		<str id="INFO_CFG_FLT_DIS_ENTR">Энтропияны өшіру</str>
		<str id="INFO_CFG_FLT_DIS_AUDIO">Дыбыс өшіру</str>
		<str id="INFO_CFG_FLT_DIS_PROCF">Өшіру ProcF</str>
		<str id="INFO_CFG_FLT_MOTION">Қозғалыс детекторы</str>
		<str id="INFO_CFG_FLT_MOTION_10X">10х қолдану</str>
		<str id="INFO_CFG_FLT_MOTION_LEVEL">Табалдырық</str>
		<str id="INFO_CFG_FLT_MOTION_AUTO_RESET">Авто қалпына келтіру</str>
		<str id="INFO_CFG_FLT_NSKIP">Кадрларды өткізу</str>
		<str id="INFO_CFG_FLT_AUTODOWNRATE">АВТО КЖБ (кадр жиілігін бөлгішті автоматты түрде таңдау)</str>
		<str id="INFO_CFG_FLT_CONTOUR">Бекіт. Контур (нысанның айналасында аура құру режимін таңдау)</str>
		<str id="INFO_CFG_FLT_CONTOUR_FACE">Тек бет</str>
		<str id="INFO_CFG_FLT_CONTOUR_FACE10">10 бет</str>
		<str id="INFO_CFG_FLT_CONTOUR_VIBRA">Vibra</str>
		<str id="INFO_CFG_FLT_STABX">Тұрақт. X</str>
		<str id="INFO_CFG_FLT_STABY">Тұрақт. Y</str>
		<str id="INFO_CFG_FLT_GLOBAL">Жалпы сүзгіні қолдану</str>
		<str id="INFO_GEOVISION_PATH">GV path</str>
		<str id="INFO_STATE_LEVEL">Қауіп шектері</str>
		<str id="INFO_STATE_LEVEL_AG">Ag</str>
		<str id="INFO_STATE_LEVEL_ST">St</str>
		<str id="INFO_STATE_LEVEL_TN">Tn</str>
		<str id="INFO_STORE_LEN">Буффер өлшемі</str>
		<str id="INFO_CFG_EEG_TEST_MODE">ЭЭГ сынағы (электроэнцефалографпен сынауды бастау)</str>
		<str id="INFO_CFG_FLT_HISTNW">Амп. бойынша гистограмма. (амплитудасы бойынша гистограмма құру (сүзгі, өзгерту қажет емес)</str>
		<str id="INFO_CFG_MODE_COLOR">Түсті кескін</str>
		<str id="INFO_CFG_FLT_CROP">Қысқарту</str>
		<str id="INFO_CFG_FLT_CROPX">X қысқарту</str>
		<str id="INFO_CFG_FLT_CROPY">Y қысқарту</str>
		<str id="INFO_CFG_FLT_CROPX_POS">ко Х бойынша қысқарту (көлденең қима кесегінің ортасы)</str>
		<str id="INFO_CFG_FLT_CROPY_POS">ко Y бойынша қысқарту (көлденең қима кесегінің ортасы)</str>
		<str id="INFO_CFG_AVG">Орташалау</str>
		<str id="INFO_CFG_AVG_ANGER">Агрессия</str>
		<str id="INFO_CFG_AVG_STRESS">Стресс</str>
		<str id="INFO_CFG_AVG_TENSION">Мазасыздық</str>
		<str id="INFO_CFG_AVG_STATE_SRC">Қауіп</str>
		<str id="INFO_CFG_AVG_ENERGY">Энергиялық</str>
		<str id="INFO_CFG_AVG_COMPAT">Үйлесімділік</str>
		<str id="INFO_CFG_AVG_DANGER">Қауіп</str>
		<str id="INFO_CFG_AVG_BALANCE">Тепе-теңдік</str>
		<str id="INFO_CFG_AVG_CHARMING">Харизматикалық</str>
		<str id="INFO_CFG_ALERTS">Ескерту</str>
		<str id="INFO_CFG_ALERT_SUSP_SND">Дыбыс (Қауіпті.)</str>
		<str id="INFO_CFG_ALERT_CUST_SND">Дыбыс (Cust)</str>
		<str id="INFO_CFG_ALERT_A_SND">Sound (A)</str>
		<str id="INFO_CFG_ALERT_S_SND">Sound (S)</str>
		<str id="INFO_CFG_ALERT_T_SND">Sound (T)</str>
		<str id="INFO_CFG_ALERT_IMAGE">Кескіндерді авто жазу</str>
		<str id="INFO_CFG_ALERT_IMAGE_AUTO">Кескіндерді авто жазу (с)</str>
		<str id="INFO_CFG_ALERT_IMAGE_AUTO_TIME">Арқылы алып тастау</str>
		<str id="INFO_CFG_ALERT_IMAGE_AUTO_FILE">Кескіндерді файлға сақтау</str>
		<str id="INFO_CFG_ALERT_IMAGE_AUTO_FILE_XML">Қосымша XML сақтау</str>
		<str id="INFO_CFG_ALERT_IMAGE_AUTO_FACE">Беттерді сақтау</str>
		<str id="INFO_CFG_ALERT_IMAGE_AUTO_PRINT">Қауіпті басып шығару</str>
		<str id="INFO_CFG_ALERT_IMAGE_AUTO_GROUP_BY">Папкалар бойынша топтау %</str>
		<str id="INFO_CFG_ALERT_IMAGE_AUTO_ORIGINAL">Дереккөзді сақтау</str>
		<str id="INFO_CFG_ALERT_IMAGE_AUTO_FACE_VALIDATE">Беттерді тексеру</str>
		<str id="INFO_CFG_ALERT_IMAGE_COUNT">N кескіндерді көрсету</str>
		<str id="INFO_CFG_ALERT_IMAGE_FORMAT">Кескін форматы</str>
		<str id="INFO_CFG_SND_PATH">Аудио файл</str>
		<str id="INFO_CFG_MACRO_ENABLE">Макро режимі</str>
		<str id="INFO_CFG_MACRO_LEVEL_L">L Шегі</str>
		<str id="INFO_CFG_MACRO_LEVEL_S">S Шегі</str>
		<str id="INFO_CFG_MACRO_AURA">Аура режимі</str>
		<str id="INFO_CFG_MACRO_FACE">Макро режим +</str>
		<str id="INFO_CFG_MACRO_FACE1">Толық</str>
		<str id="INFO_CFG_MACRO_FACE2">Тек бет</str>
		<str id="INFO_CFG_FACE_ENABLE">Беттерді іздеу</str>
		<str id="INFO_CFG_FACE_QUALITY">Іздеу сапасы [1..4]</str>
		<str id="INFO_CFG_FACE_SCALE">Масштаб 1: X</str>
		<str id="INFO_CFG_FACE_QUALITY_SIZE_MIN">Мин өлшемі</str>
		<str id="INFO_CFG_FACE_QUALITY_SIZE_MAX">Макс өлшемі</str>
		<str id="INFO_CFG_FACE_DRAW">Контурларды көрсету</str>
		<str id="INFO_CFG_FACE_PATH">Орнату</str>
		<str id="INFO_CFG_FACE_MODE_SYNC">Синхрондалған режим</str>
		<str id="INFO_CFG_QTEST">Сапа сынағы</str>
		<str id="INFO_CFG_QTEST_ENABLE">Қосу</str>
		<str id="INFO_CFG_QTEST_LEVEL_LIGHT">Жарық деңгейі</str>
		<str id="VI_INFO_QTEST_FPS_MIN">К/ж мин (кадр жиілігі)</str>
		<str id="VI_INFO_QTEST_FPS_MAX">К/ж макс (кадр жиілігі)</str>
		<str id="VI_INFO_QTEST_FACE_DELAY">Беттерді іздеуді кешіктіру</str>
		<str id="INFO_CFG_SND">Vibra-дыбыс</str>
		<str id="INFO_CFG_SND_KILL">Негізгі дыбысты өшіру</str>
		<str id="INFO_CFG_SND_NONE">Дыбыссыз</str>
		<str id="INFO_CFG_SND_CR">CG</str>
		<str id="INFO_CFG_SND_CG">CR</str>
		<str id="INFO_CFG_SND_HR">HG</str>
		<str id="INFO_CFG_SND_HG">HR</str>
		<str id="INFO_CFG_SND_SR">SR</str>
		<str id="INFO_CFG_SND_SG">SG</str>
		<str id="INFO_CFG_SND_TITLE">Brain voice</str>
		<str id="INFO_CFG_VI_DEVICE">VI құрылғы</str>
		<str id="INFO_CFG_VI_DEVICE_INDICATION">Көрсеткіш</str>
		<str id="INFO_CORRELATION_ENABLE">Корреляцияны қосу</str>
		<str id="INFO_CORRELATION_MEDIAN">Медиана режимі</str>
		<str id="INFO_CORRELATION_T">Кезең</str>
		<str id="INFO_CORRELATION_TAUTO">Авто ығыстыру</str>
		<str id="INFO_CORRELATION_SORT">Сұрыптау</str>
		<str id="INFO_CORRELATION_HIPASS">ЖЖ сүзгісі (жоғары жиілікті сүзгі)</str>
		<str id="INFO_CORRELATION_LOPASS">ТЖ сүзгісі (төмен жиілікті сүзгі)</str>
		<str id="INFO_CORRELATION_AVG">Орташалау</str>
		<str id="INFO_LD_GROUP">Жалғандық детекциясы</str>
		<str id="INFO_LD_ENABLE">Қосулы</str>
		<str id="INFO_LD_PERIOD">Өңдеу кезеңі (с)</str>
		<str id="INFO_LD_PERIOD_BASE">Салыстыру кезеңі (с)</str>
		<str id="INFO_LD_LTH">Рұқсат етілген шегі</str>
		<str id="INFO_LD_AUDIO_SENSITIVITY">Дыбыс сезімі (с)</str>
		<str id="INFO_LD_NAME">ЖАЛҒАНДЫҚ</str>
		<str id="INFO_LD_MODE">Іске қосу режимі</str>
		<str id="INFO_LD_MODE_AUTO">Авто</str>
		<str id="INFO_LD_MODE_AUDIO">Дыбыс </str>
		<str id="INFO_LD_MODE_MANUAL">Қолмен</str>
		<str id="INFO_LD_MODE_CMP">Салыстыру</str>
		<str id="INFO_LD_MODE_OPPOSITE">Кері санақ</str>
		<str id="INFO_LD_MODE_TEXT">Мәтін</str>
		<str id="INFO_AVI_GROUP">Бейнені қармап алу</str>
		<str id="INFO_AVI_SETTINGS">Баптаулар...</str>
		<str id="INFO_AVI_CAPTURE">Жазуды бастау</str>
		<str id="INFO_AVI_PATH">Жазуға арналған каталог</str>
		<str id="INFO_GRAPH_GROUP">Графиктер</str>
		<str id="INFO_GRAPH_PERIOD">Кезең (с)</str>
		<str id="INFO_GRAPH_DIF_PERIOD">Орташалау (с)</str>
		<str id="INFO_GRAPH_HIST_PERIOD">Гистограмма (с)</str>
		<str id="INFO_HIST_A_PERIOD">H (C) гистограммасын орташалау</str>
		<str id="INFO_HIST_F_PERIOD">S (с) гистограммасын орташалау</str>
		<str id="INFO_HIST_C_PERIOD">C (с) гистограммасын орташалау</str>
		<str id="INFO_STAT_SUB_SHOW">Көрсету</str>
		<str id="INFO_STAT_SUB_SHOW2">График2</str>
		<str id="INFO_STAT_SUB_CALC">Есептеу</str>
		<str id="INFO_STAT_SUB_DIF">Салыст. режим</str>
		<str id="INFO_STAT_SUB_AUTO">авто</str>
		<str id="INFO_STAT_SUB_VMIN">vMin</str>
		<str id="INFO_STAT_SUB_VMAX">vMax</str>
		<str id="INFO_STAT_SUB_GMIN">gMin</str>
		<str id="INFO_STAT_SUB_GMAX">gMax</str>
		<str id="INFO_STAT_SUB_RATE1">R1 V</str>
		<str id="INFO_STAT_SUB_RATE2">R2 V</str>
		<str id="INFO_STAT_SUB_RATE1V">R1 C</str>
		<str id="INFO_STAT_SUB_RATE2V">R2 C</str>
		<str id="INFO_STAT_SUB_LEVEL">Шегі</str>
		<str id="INFO_STAT_SUB_GFLTLFAVG">Орташа ЖЖ (орташа жоғары жиілікті сүзгі)</str>
		<str id="INFO_STAT_SUB_GFLTLF">ЖЖ сүзгісі (жоғары жиілікті сүзгі)</str>
		<str id="INFO_STAT_SUB_GFLTHF">ТЖ сүзгісі (төмен жиілікті сүзгі)</str>
		<str id="INFO_STAT_COL_NAME">Параметр</str>
		<str id="INFO_STAT_COL_VAR">V</str>
		<str id="INFO_STAT_COL_CMIN">cMin</str>
		<str id="INFO_STAT_COL_CMAX">cMax</str>
		<str id="INFO_STAT_COL_BMIN">bMin</str>
		<str id="INFO_STAT_COL_BMAX">bMax</str>
		<str id="INFO_STATAVG_COL_NAME">Параметр</str>
		<str id="INFO_STATAVG_COL_VAR">V</str>
		<str id="INFO_STATAVG_COL_S">S</str>
		<str id="INFO_STATAVG_COL_PI">Vi</str>
		<str id="INFO_STATAVG_COL_CMIN">cMin</str>
		<str id="INFO_STATAVG_COL_CMAX">cMax</str>
		<str id="INFO_STATAVG_COL_BMIN">bMin</str>
		<str id="INFO_STATAVG_COL_BMAX">bMax</str>
		<str id="INFO_STATAVG_COL_NMIN">N Min</str>
		<str id="INFO_STATAVG_COL_NMAX">N Max</str>
		<str id="INFO_STATAVG_PROGRESS">Дайындық</str>
		<str id="INFO_STATAVG_PERIOD">Ұзақтығы (с)</str>
		<str id="INFO_STATAVG_OPEN">Нәтижені ашу</str>
		<str id="INFO_STAT_A1X">A1 (fast)</str>
		<str id="INFO_STAT_A4X">A4 (fast)</str>
		<str id="INFO_STAT_A1">A1</str>
		<str id="INFO_STAT_A2">A2</str>
		<str id="INFO_STAT_A3">A3</str>
		<str id="INFO_STAT_A4">A4</str>
		<str id="INFO_STAT_A5">A5</str>
		<str id="INFO_STAT_A6">A6</str>
		<str id="INFO_STAT_A7">A7</str>
		<str id="INFO_STAT_A8">A8</str>
		<str id="INFO_STAT_A9">A9</str>
		<str id="INFO_STAT_F1X">F1 (fast)</str>
		<str id="INFO_STAT_F1D">dF1 (fast)</str>
		<str id="INFO_STAT_F1">F1</str>
		<str id="INFO_STAT_F2">F2</str>
		<str id="INFO_STAT_F3">F3</str>
		<str id="INFO_STAT_F4">F4</str>
		<str id="INFO_STAT_F5XT">F5 мазасыздық</str>
		<str id="INFO_STAT_F5X">F5 (fast)</str>
		<str id="INFO_STAT_F5X_TEXT">Мазасыздық (F5X)</str>
		<str id="INFO_STAT_F5">F5</str>
		<str id="INFO_STAT_F6">F6</str>
		<str id="INFO_STAT_F6_TEXT">Тежеу (F6)</str>
		<str id="INFO_STAT_F7">F7</str>
		<str id="INFO_STAT_F8">F8</str>
		<str id="INFO_STAT_F9">F9</str>
		<str id="INFO_STAT_F9_TEXT">Невротизм (F9)</str>
		<str id="INFO_STAT_S1">S1</str>
		<str id="INFO_STAT_S2">S2</str>
		<str id="INFO_STAT_S3">S3</str>
		<str id="INFO_STAT_S4">S4</str>
		<str id="INFO_STAT_S5">S5</str>
		<str id="INFO_STAT_S6">S6</str>
		<str id="INFO_STAT_S7">S7</str>
		<str id="INFO_STAT_S8">S8</str>
		<str id="INFO_STAT_S9">S9</str>
		<str id="INFO_STAT_IP">P</str>
		<str id="INFO_STAT_DP5">dP5</str>
		<str id="INFO_STAT_II2">I</str>
		<str id="INFO_STAT_IE2">E</str>
		<str id="INFO_STAT_P1">P1</str>
		<str id="INFO_STAT_P2">P2</str>
		<str id="INFO_STAT_P3">P3</str>
		<str id="INFO_STAT_P4">P4</str>
		<str id="INFO_STAT_P5">P5 өтірік</str>
		<str id="INFO_STAT_P6">P6 стр</str>
		<str id="INFO_STAT_P6_TEXT">Стресс (P6)</str>
		<str id="INFO_STAT_P7">P7 агр</str>
		<str id="INFO_STAT_P7_TEXT">Агрессия (P7)</str>
		<str id="INFO_STAT_P6A">P6A стр</str>
		<str id="INFO_STAT_P7A">P7A агр</str>
		<str id="INFO_STAT_P6F">P6F стр</str>
		<str id="INFO_STAT_P7F">P7F агр</str>
		<str id="INFO_STAT_P8">P8 эн</str>
		<str id="INFO_STAT_P8_TEXT">Энергичность (P8)</str>
		<str id="INFO_STAT_P8A">P8A эн</str>
		<str id="INFO_STAT_P8F">P8F эн</str>
		<str id="INFO_STAT_P9">P9 H</str>
		<str id="INFO_STAT_P9A">P9A H</str>
		<str id="INFO_STAT_P9F">P9F H</str>
		<str id="INFO_STAT_P10">P10 Δ</str>
		<str id="INFO_STAT_P10A">P10A Δ</str>
		<str id="INFO_STAT_P10F">P10F Δ</str>
		<str id="INFO_STAT_P11">P11 æ</str>
		<str id="INFO_STAT_P11A">P11A æ</str>
		<str id="INFO_STAT_P11F">P11F æ</str>
		<str id="INFO_STAT_P12">P12 S</str>
		<str id="INFO_STAT_P12A">P12A S</str>
		<str id="INFO_STAT_P12F">P12F S</str>
		<str id="INFO_STAT_P13">P13</str>
		<str id="INFO_STAT_P14">P14</str>
		<str id="INFO_STAT_P15">P15</str>
		<str id="INFO_STAT_P16">P16 CN</str>
		<str id="INFO_STAT_P16_TEXT">Тұрақты (P16)</str>
		<str id="INFO_STAT_P17">P17 CS</str>
		<str id="INFO_STAT_P17_TEXT">Харизматикалық (P17)</str>
		<str id="INFO_STAT_P18">P18 Com</str>
		<str id="INFO_STAT_P18_TEXT">Өзін-өзі реттеу (P18)</str>
		<str id="INFO_STAT_P19">P19 Оп</str>
		<str id="INFO_STAT_P19_TEXT">Қауіп (P19)</str>
		<str id="INFO_STAT_P20">P20 LD</str>
		<str id="INFO_STAT_P20_TEXT">LD (P20)</str>
		<str id="INFO_STAT_P21">P21 Денсаулық</str>
		<str id="INFO_STAT_P21_TEXT">Денсаулық(P21)</str>
		<str id="INFO_STAT_P22">P22 Денсаулық'</str>
		<str id="INFO_STAT_P22_TEXT">Денсаулық' (P22)</str>
		<str id="INFO_STAT_P23">P23 ΣVi</str>
		<str id="INFO_STAT_P23_TEXT">ΣVi (P23)</str>
		<str id="INFO_STAT_P24">P24 Сон</str>
		<str id="INFO_STAT_P24_TEXT">Ұйқышылдық (P24)</str>
		<str id="INFO_STAT_P25">P25 VSlp</str>
		<str id="INFO_STAT_P25_TEXT">VSlp (P25)</str>
		<str id="INFO_STAT_P26">P26 Extr</str>
		<str id="INFO_STAT_P26_TEXT">Экстраверсия (P26)</str>
		<str id="INFO_STAT_P27">P27 Stab</str>
		<str id="INFO_STAT_P27_TEXT">Тұрақтылық (P27)</str>
		<str id="INFO_STAT_P29">DP</str>
		<str id="INFO_STAT_P29_TEXT">Депрессия (P29)</str>
		<str id="INFO_STAT_P30">HP</str>
		<str id="INFO_STAT_P30_TEXT">Бақыт (P30)</str>
		<str id="INFO_STAT_P36">AI</str>
		<str id="INFO_STAT_P36_TEXT">AI(P36)</str>
		<str id="INFO_STAT_P37">AIc</str>
		<str id="INFO_STAT_P37_TEXT">AI current (P36)</str>
		<str id="INFO_STAT_P38">AIf</str>
		<str id="INFO_STAT_P38_TEXT">AI final(P36)</str>
		<str id="INFO_STAT_P41">AI</str>
		<str id="INFO_STAT_P41_TEXT">AI value(P41)</str>
		<str id="INFO_STAT_C1">C1</str>
		<str id="INFO_STAT_C2">C2</str>
		<str id="INFO_STAT_C3">C3</str>
		<str id="INFO_STAT_C4">C4</str>
		<str id="INFO_STAT_HISTFN">HC. Функция (Гистограмма функциясын таңдау)</str>
		<str id="INFO_STAT_SIN">sin(t*2*pi*n)</str>
		<str id="INFO_ENGINE_MSND">белгі туралы ескерту</str>
		<str id="INFO_ENGINE_RSND">қалпына келтіру туралы ескерту</str>
		<str id="INFO_CFG_FLT_F6_HI">F6 НЧ</str>
		<str id="INFO_CFG_FLT_F6_LO">F6 ВЧ</str>
		<str id="INFO_CFG_FLT_F6_N">F6 N</str>
		<str id="INFO_CFG_FLT_CAMPOS">Тұрақтандырғыш</str>
		<str id="INFO_CFG_FLT_FPSDIV">Сүзгі К/Ж (кадр жиілігі)</str>
		<str id="INFO_CFG_FLT_DISTORTION">E-Monster</str>
		<str id="INFO_CFG_FTP">Network Storage</str>
		<str id="INFO_CFG_FTP_ENABLE">enable FTP</str>
		<str id="INFO_CFG_FTP_PATH">configuration file</str>
		<str id="INFO_CFG_HTTP_URL">HTTP url</str>
		<str id="INFO_STAT_FN01">X1</str>
		<str id="INFO_STAT_FN02">X2</str>
		<str id="INFO_STAT_FN03">X3</str>
		<str id="INFO_STAT_FN04">X4</str>
		<str id="INFO_STAT_FN05">X5</str>
		<str id="INFO_STAT_FN06">X6</str>
		<str id="INFO_STAT_FN07">X7</str>
		<str id="INFO_STAT_FN08">X8</str>
		<str id="INFO_STAT_FN09">X9</str>
		<str id="INFO_STAT_FN10">X10</str>
		<str id="INFO_USER_CURRENT">Ағымдағы жазба</str>
		<str id="INFO_USER_NEW">Жаңа жазба...</str>
		<str id="INFO_USER_NEW_NAME">ТАӘ</str>
		<str id="INFO_USER_NEW_BD">Туған күні</str>
		<str id="INFO_USER_NEW_ADD">Қосымша</str>
		<str id="INFO_USER_DB_PATH">ДҚ каталогы...</str>
		<str id="INFO_USER_DB_MODE">ДҚ режимі</str>
		<str id="DB_MODE_MANUAL">қолмен</str>
		<str id="DB_MODE_KEY_ONLY">тек енгізу</str>
		<str id="INFO_USER_AVI_GROUP">Жазу</str>
		<str id="INFO_USER_AVI_TMAX">макс. (с)</str>
		<str id="INFO_USER_AVI_PURGE">жою (Mb)</str>
		<str id="INFO_USER_INFO">Дербес деректер</str>
		<str id="INFO_USER_INFO_NAME">Аты</str>
		<str id="INFO_USER_INFO_ID">ID</str>
		<str id="INFO_USER_INFO_BD">туған күні</str>
		<str id="INFO_USER_INFO_GENDER">Жынысы</str>
		<str id="INFO_USER_INFO_AGE">Жасы</str>
		<str id="INFO_USER_INFO_COMMENTS">Қосымша</str>
		<str id="INFO_USER_AUTO_MARKERS_CQ">CQ маркерлер</str>
		<str id="INFO_USER_AUTO_MARKERS_RQ">RQ маркерлер</str>
		<str id="INFO_USER_AUTO_MARKERS_SET">Маркерлерді орнату</str>
		<str id="INFO_CAPTURE_TIMER">таймер</str>
		<str id="INFO_CAPTURE_STOP_IN">тоқта</str>
		<str id="INFO_CAPTURE_STOP_AT">тоқтату</str>
		<str id="INFO_CAPTURE_START_AT">бастау</str>
		<str id="INFO_CAPTURE_EXTRA_SRC">сақтау шығ.</str>
		<str id="INFO_CAPTURE_EXTRA">ҚА сақтау (қосымша ақпаратты сақтау)</str>
		<str id="INFO_CAPTURE_XML">XML Сақтау</str>
		<str id="INFO_CAPTURE_TXT">TXT Сақтау</str>
		<str id="INFO_CAPTURE_DTF">DTF Сақтау</str>
		<str id="INFO_CAPTURE_LD">LD Сақтау</str>
		<str id="INFO_CAPTURE_HTTP">HTTP Күй</str>
		<str id="INFO_CAPTURE_FACE_IMG">Беттерді сақтау</str>
		<str id="INFO_CAPTURE_IS">Жазу режимі</str>
		<str id="INFO_CAPTURE_IS_AVI">AVI</str>
		<str id="INFO_CAPTURE_IS_IMG">IMG</str>
		<str id="INFO_CAPTURE_COM">СОМ шығару</str>
		<str id="INFO_NET_GROUP">Желі</str>
		<str id="INFO_NET_ENABLE">Желі арқылы беру</str>
		<str id="INFO_NET_STATE_CRITICAL">Сыни деңгей %</str>
		<str id="INFO_NET_STATE_CUSTOMER">Клиенттік деңгей %</str>
		<str id="INFO_NET_STATE_CRITICAL_S">аудан к-ті %</str>
		<str id="INFO_NET_STATE_CRITICAL_K">маңыздылық к-ті %</str>
		<str id="INFO_NET_DIRECT_VIDEO">Толық бейне ағыны</str>
		<str id="INFO_NET_LOCAL_TCP">Жергілікті TCP порты</str>
		<str id="INFO_NET_HOST_GR">Терминал</str>
		<str id="INFO_NET_HOST_IP">IP</str>
		<str id="INFO_NET_HOST_ENABLED">Енгізілген</str>
		<str id="INFO_NET_PORT_TCP">TCP порт</str>
		<str id="INFO_NET_PORT_UDP">UDP порт</str>
		<str id="INFO_NET_COMPRESSION">Бейнені қысу</str>
		<str id="LOGLD_LIE_DETECTED">Жалғандық анықталды</str>
		<str id="LOGLD_LIE_TIME_FROM">Басталу уақыты</str>
		<str id="LOGLD_LIE_TIME_TO">Аяқталу уақыты</str>
		<str id="LOGLD_LIE_TIME_FROM_VIDEO">Бейне таймер басталуы</str>
		<str id="LOGLD_LIE_TIME_TO_VIDEO">Бейне таймер аяқталуы</str>
		<str id="LOGLD_LIE_TIME">LD уақыты</str>
		<str id="LOGLD_LIE_TIME_VIDEO">LD бейне таймер</str>
		<str id="LOGLD_LIE_QUESTION">N сұрақ</str>
		<str id="HINT_GRAPH_ENABLE">Кесте</str>
		<str id="HINT_STAT_CALC">Есептеу</str>
		<str id="HINT_HIST_R">Қызыл (қызыл түсті графикпен көрсету)</str>
		<str id="HINT_HIST_G">Жасыл (жасыл түсті графикпен көрсету)</str>
		<str id="HINT_CORREL_ENABLE">Корреляция</str>
		<str id="HINT_RECT_VI0">VI N(%i)</str>
		<str id="HINT_RECT_VI1">VI 10(%i)</str>
		<str id="HINT_RECT_VI2">VI 2(%i)</str>
		<str id="HINT_RECT_SRC">SRC</str>
		<str id="HINT_RECT_DELTA">DELTA</str>
		<str id="HINT_RECT_VI0_A">VI N A(%i)</str>
		<str id="HINT_RECT_VI1_A">VI 10 A(%i)</str>
		<str id="HINT_RECT_VI2_A">VI 2 A(%i)</str>
		<str id="HINT_RECT_SRC_A">SRC A</str>
		<str id="HINT_RECT_DELTA_A">DELTA A</str>
		<str id="HINT_RECT_DELTA_FA">DELTA FA</str>
		<str id="HINT_RECT_VI0_B">VI N F(%i)</str>
		<str id="HINT_RECT_VI1_B">VI 10 F(%i)</str>
		<str id="HINT_RECT_VI2_B">VI 2 F(%i)</str>
		<str id="HINT_RECT_SRC_B">SRC F</str>
		<str id="HINT_RECT_DELTA_B">DELTA F</str>
		<str id="HINT_RECT_DELTA_FB">DELTA FF</str>
		<str id="HINT_RECT_HIST_X">Hist. X</str>
		<str id="HINT_RECT_HIST_Y">Hist. Y</str>
		<str id="MESSAGE_ERROR">Қате!</str>
		<str id="MESSAGE_WARNING">Назар аударыңыз!</str>
		<str id="MESSAGE_LD_WARNING_FACE">Назар аударыңыз! Төмен сапа (1)</str>
		<str id="MESSAGE_LD_WARNING_LIGHT">Назар аударыңыз! Төмен сапа (2)</str>
		<str id="MESSAGE_LD_WARNING_FPS">Назар аударыңыз! Төмен сапа (3)</str>
		<str id="MESSAGE_BROWSE_FOR_DB">Дерекқор каталогы</str>
		<str id="MESSAGE_CANT_CREATE_AVI_FILE">Файл құру мүмкін емес!</str>
		<str id="MESSAGE_CANT_START_AVI_FILE">Файл құру мүмкін емес!\n%s</str>
		<str id="MESSAGE_NEED_RESTART">Бағдарламаны қайта бастау керек!</str>
		<str id="MESSAGE_CANT_CREATE_FOLDER">Папка жасау мүмкін емес!\n%s</str>
		<str id="MESSAGE_CANT_WRITE_FILE">Файлға жазу қатесі !</str>
		<str id="MESSAGE_DELETE_SELECTED_RECORDS">Бөлектелген жазбаларды жою керек пе ?</str>
		<str id="MESSAGE_AVI_PURGE_STOP">Дискіде орын жеткіліксіз!\ пЖазба тоқтатылды .</str>
		<str id="MESSAGE_CANT_RECOMPRESS">Форматтарды түрлендіру мүмкін емес!</str>
		<str id="MESSAGE_EXCEL_VERSION">Бағдарлама жұмыс істеуі үшін  Microsoft Excel 2010 нұсқасынан төмен емес нұсқа қажет</str>
		<str id="STR_FRAME_CAPTION">Vibraimage</str>
		<str id="STR_FILE_FILTER_AVI_VI">Барлық форматтар (*.avi;*. asf;*. mp4;*. xml)|*. avi;*. asf;*. mp4;*. xml|AVI файлдары (*. avi;*.asf;*. mp4)|*. avi;*. asf;*.mp4|VI файлдары ( * .xml)|*.xml /Барлық файлдар (*.*)|*.*|</str>
		<str id="STR_FILE_FILTER_VI">VI файлы (*.xml)|*.xml|Все файлы (*.*)|*.*|</str>
		<str id="STR_FILE_FILTER_AVI">AVI файлы (*.avi;*.asf;*.mp4)|*.avi;*.asf;*.mp4|Все файлы (*.*)|*.*|</str>
		<str id="STR_FILE_FILTER_AVI_ZIP">барлық форматтар (*.avi;*.asf;*.mp4;*.zip)|*.zip;*.avi;*.asf;*.mp4|AVI файлы (*.avi;*.asf;*.mp4)|*.avi;*.asf;*.mp4|ZIP файлы (*.zip)|*.zip|All files (*.*)|*.*|</str>
		<str id="STR_FILE_FILTER_HIST">VI файлы (*.xml)|*.xml|Все файлы (*.*)|*.*|</str>
		<str id="STR_FILE_FILTER_IMG_ALL">барлық форматтар (*.png;*.bmp;*.jpg;*.gif)|*.png;*.bmp;*.jpg;*.gif|PNG файлы (*.png)|*.png|BMP файлы (*.bmp)|*.bmp|JPG файлы (*.jpg)|*.jpg|GIF файлы (*.gif)|*.gif|Все файлы (*.*)|*.*|</str>
		<str id="STR_FILE_FILTER_ALL">барлық файлдар (*.*)|*.*|</str>
		<str id="STR_FILE_FILTER_XML">XML файлы (*.xml)|*.xml|Все файлы (*.*)|*.*|</str>
		<str id="STR_FILE_FILTER_XML_TXT">XML файлы (*.xml)|*.xml|TXT файлы (*.txt)|*.txt|Все файлы (*.*)|*.*|</str>
		<str id="STR_FILE_FILTER_TXT_AVI">TXT файлы (*.txt)|*.txt|AVI файлы (*.avi;*.asf;*.mp4)|*.avi;*.asf;*.mp4|Все файлы (*.*)|*.*|</str>
		<str id="STR_FILE_FILTER_XML_AVI">XML файлы (*.xml)|*.xml|AVI файлы (*.avi;*.asf;*.mp4)|*.avi;*.asf;*.mp4|Все файлы (*.*)|*.*|</str>
		<str id="STR_FILE_FILTER_LDQ">LD файлы (*.ldq)|*.ldq|Все файлы (*.*)|*.*|</str>
		<str id="STR_FILE_FILTER_REG">Reg файлы (*.reg)|*.reg|Все файлы (*.*)|*.*|</str>
		<str id="STR_UNITS_PSY">Psy</str>
		<str id="STR_UNITS_EKKAL">E [ккал/мин]</str>
		<str id="STR_UNITS_FPS">к/с (секундына кадрлар)</str>
		<str id="STR_UNITS_S">с (секундтар)</str>
		<str id="STR_AURAVI">Aura VI</str>
		<str id="STR_MONSTER">Құбыжық VI</str>
		<str id="STR_BIOTESTER">БиоТестер</str>
		<str id="STR_SLEEPINESS">Ұйқышылдық</str>
		<str id="SEQ_OWNER">Пайдалану құқығы:</str>
		<str id="SEQ_SERIAL">Нөмірі:</str>
		<str id="SEQ_TYPE">Лицензия:</str>
		<str id="SEQ_DEMO">Демо</str>
		<str id="SEQ_PROF">Professional</str>
		<str id="SEQ_LIMITED">Limited</str>
		<str id="SEQ_UNLIMITED">Unlimited</str>
		<str id="NETSTATUS_IMAGE">Image</str>
		<str id="NETSTATUS_CONFIG">Settings</str>
		<str id="NETSTATUS_CFG_MODL">Модуль</str>
		<str id="NETSTATUS_CFG_MODL_IP">IP</str>
		<str id="NETSTATUS_CFG_MODL_PORT_TCP">TCP порт</str>
		<str id="NETSTATUS_CFG_LOCAL">Терминал</str>
		<str id="NETSTATUS_CFG_LOCAL_PORT_TCP">TCP порт</str>
		<str id="NETSTATUS_CFG_LOCAL_PORT_UDP">UDP порт</str>
		<str id="NETSTATUS_CFG_ALERTS">Ескерту</str>
		<str id="NETSTATUS_CFG_ALERT_SOUND">Дыбыстар</str>
		<str id="NETSTATUS_CFG_ALERT_IMAGE">Кескіндер</str>
		<str id="AMCAP_DLG_VIDEO_FORMAT">Бейне форматы...</str>
		<str id="AMCAP_DLG_VIDEO_SOURCE">Бейне көзі...</str>
		<str id="AMCAP_DLG_VIDEO_DISPLAY">Бейнені көрсету...</str>
		<str id="AMCAP_DLG_AUDIO_CAP_FILTER">Дыбыс сүзгісі...</str>
		<str id="AMCAP_DLG_VIDEO_CAP_FILTER">Бейне сүзгісі...</str>
		<str id="AMCAP_DLG_VIDEO_CAP_FORMAT">Бейне жазу форматы...</str>
		<str id="AMCAP_DLG_VIDEO_PREVIEW_FORMAT">Бейне көру форматы...</str>
		<str id="AMCAP_DLG_VIDEO_CROSSBAR">Бейне қосылымдары...</str>
		<str id="AMCAP_DLG_VIDEO_CROSSBAR2">Бейне қосылымдары2...</str>
		<str id="AMCAP_DLG_TV_TUNER">ТД сигналы...</str>
		<str id="AMCAP_DLG_AUDIO_CAP_FORMAT">Дыбысты жазу форматы...</str>
		<str id="AMCAP_DLG_TV_AUDIO">ТД дыбысы...</str>
		<str id="STR_ARCHIVE_FOLDER">мұрағат папкасы...</str>
		<str id="NETAVIS_TITLE">Net AVI Server</str>
		<str id="VI_GRAPH_AVG_ALL">Pulse AVG_ALL</str>
		<str id="VI_GRAPH_SIGMA_ALL">Pulse SIGMA_ALL</str>
		<str id="VI_GRAPH_AVG_ZONE">Pulse AVG_ZONE1</str>
		<str id="VI_GRAPH_SIGMA_ZONE">Pulse SIGMA_ZONE1</str>
		<str id="VI_GRAPH_AVG_ZONE2">Pulse AVG_ZONE2</str>
		<str id="VI_GRAPH_SIGMA_ZONE2">Pulse SIGMA_ZONE2</str>
		<str id="VI_GRAPH_AVG_LINE1">Pulse AVG_LINE1</str>
		<str id="VI_GRAPH_SIGMA_LINE1">Pulse SIGMA_LINE1</str>
		<str id="VI_GRAPH_AVG_LINE2">Pulse AVG_LINE2</str>
		<str id="VI_GRAPH_SIGMA_LINE2">Pulse SIGMA_LINE2</str>
		<str id="VI_GRAPH_AVG_LINE3">Pulse AVG_LINE3</str>
		<str id="VI_GRAPH_SIGMA_LINE3">Pulse SIGMA_LINE3</str>
		<str id="VI_GRAPH_SIN">Pulse SIN</str>
		<str id="VI_GRAPH_PHASE_T">Pulse PHASE_T</str>
		<str id="VI_GRAPH_PHASE_A">Pulse PHASE_A</str>
		<str id="VI_GRAPH_PULSE10">Pulse PULSE10</str>
		<str id="VI_GRAPH_AVG_X0">Pulse AVG_X0</str>
		<str id="VI_GRAPH_AVG_X1">Pulse AVG_X1</str>
		<str id="VI_GRAPH_AVG_X2">Pulse AVG_X2</str>
		<str id="VI_GRAPH_AVG_X3">Pulse AVG_X3</str>
		<str id="VI_GRAPH_AVG_X4">Pulse AVG_X4</str>
		<str id="VI_GRAPH_AVG_X5">Pulse AVG_X5</str>
		<str id="VI_GRAPH_AVG_X6">Pulse AVG_X6</str>
		<str id="VI_GRAPH_AVG_X7">Pulse AVG_X7</str>
		<str id="VI_GRAPH_AVG_X8">Pulse AVG_X8</str>
		<str id="VI_GRAPH_AVG_X9">Pulse AVG_X9</str>
		<str id="VI_GRAPH_SIGMA_X0">Pulse SIGMA_X0</str>
		<str id="VI_GRAPH_SIGMA_X1">Pulse SIGMA_X1</str>
		<str id="VI_GRAPH_SIGMA_X2">Pulse SIGMA_X2</str>
		<str id="VI_GRAPH_SIGMA_X3">Pulse SIGMA_X3</str>
		<str id="VI_GRAPH_SIGMA_X4">Pulse SIGMA_X4</str>
		<str id="VI_GRAPH_SIGMA_X5">Pulse SIGMA_X5</str>
		<str id="VI_GRAPH_SIGMA_X6">Pulse SIGMA_X6</str>
		<str id="VI_GRAPH_SIGMA_X7">Pulse SIGMA_X7</str>
		<str id="VI_GRAPH_SIGMA_X8">Pulse SIGMA_X8</str>
		<str id="VI_GRAPH_SIGMA_X9">Pulse SIGMA_X9</str>
		<str id="COM1">COM1</str>
		<str id="COM2">COM2</str>
		<str id="COM3">COM3</str>
		<str id="COM4">COM4</str>
		<str id="COM5">COM5</str>
		<str id="COM6">COM6</str>
		<str id="COM7">COM7</str>
		<str id="COM8">COM8</str>
		<str id="ERROR_LICENSE">Лицензияны тексеру мүмкін болмады</str>
		<str id="VI_INFO_STARTUP">Іске қосу</str>
		<str id="VI_INFO_PWD1">Құпия сөз</str>
		<str id="VI_INFO_PWD2">Құпия сөзді қайталау</str>
		<str id="VI_INFO_PWD_NEW">Құпия сөзді орнату</str>
		<str id="VI_INFO_PWD0">Ағымдағы құпия сөз</str>
		<str id="INFO_CAMERA_LOCK">Камера блогы</str>
</config>
